pinecone_plugins/records/__init__.py
pinecone_plugins/records/create_index_for_model.py
pinecone_plugins/records/db_control/core/client/__init__.py
pinecone_plugins/records/db_control/core/client/api/__init__.py
pinecone_plugins/records/db_control/core/client/api/manage_indexes_api.py
pinecone_plugins/records/db_control/core/client/api_client.py
pinecone_plugins/records/db_control/core/client/apis/__init__.py
pinecone_plugins/records/db_control/core/client/configuration.py
pinecone_plugins/records/db_control/core/client/exceptions.py
pinecone_plugins/records/db_control/core/client/model/__init__.py
pinecone_plugins/records/db_control/core/client/model/collection_list.py
pinecone_plugins/records/db_control/core/client/model/collection_model.py
pinecone_plugins/records/db_control/core/client/model/configure_index_request.py
pinecone_plugins/records/db_control/core/client/model/configure_index_request_embed.py
pinecone_plugins/records/db_control/core/client/model/configure_index_request_spec.py
pinecone_plugins/records/db_control/core/client/model/configure_index_request_spec_pod.py
pinecone_plugins/records/db_control/core/client/model/create_collection_request.py
pinecone_plugins/records/db_control/core/client/model/create_index_for_model_request.py
pinecone_plugins/records/db_control/core/client/model/create_index_for_model_request_embed.py
pinecone_plugins/records/db_control/core/client/model/create_index_request.py
pinecone_plugins/records/db_control/core/client/model/deletion_protection.py
pinecone_plugins/records/db_control/core/client/model/error_response.py
pinecone_plugins/records/db_control/core/client/model/error_response_error.py
pinecone_plugins/records/db_control/core/client/model/index_list.py
pinecone_plugins/records/db_control/core/client/model/index_model.py
pinecone_plugins/records/db_control/core/client/model/index_model_spec.py
pinecone_plugins/records/db_control/core/client/model/index_model_status.py
pinecone_plugin_records-1.1.0.dist-info/LICENSE.txt
pinecone_plugin_records-1.1.0.dist-info/METADATA
pinecone_plugin_records-1.1.0.dist-info/WHEEL
pinecone_plugin_records-1.1.0.dist-info/RECORD
